chgk_rating_client/__init__.py
chgk_rating_client/main.py
chgk_rating_client-1.0.2.dist-info/LICENSE
chgk_rating_client-1.0.2.dist-info/METADATA
chgk_rating_client-1.0.2.dist-info/WHEEL
chgk_rating_client-1.0.2.dist-info/top_level.txt
chgk_rating_client-1.0.2.dist-info/RECORD
