Metadata-Version: 2.1
Name: chgk-rating-client
Version: 1.0.2
Summary: Клиент для API rating.chgk.info
Home-page: https://github.com/razumau/chgk_rating_client
Author: Jury Razumau
Author-email: jurazumau@gmal.com
License: UNKNOWN
Platform: UNKNOWN
Classifier: Programming Language :: Python :: 3
Classifier: License :: OSI Approved :: MIT License
Classifier: Operating System :: OS Independent
Requires-Python: >=3.6
Requires-Dist: requests (==2.21)
Requires-Dist: logzero (==1.5.0)
Requires-Dist: redis (==3.3.8)
